sanic_conf.py
sanic_conf-0.0.7.dist-info/LICENSE
sanic_conf-0.0.7.dist-info/METADATA
sanic_conf-0.0.7.dist-info/WHEEL
sanic_conf-0.0.7.dist-info/top_level.txt
sanic_conf-0.0.7.dist-info/RECORD
